geoip2/__init__.py
geoip2/database.py
geoip2/errors.py
geoip2/mixins.py
geoip2/models.py
geoip2/py.typed
geoip2/records.py
geoip2/types.py
geoip2/webservice.py
geoip2-4.8.1.dist-info/LICENSE
geoip2-4.8.1.dist-info/METADATA
geoip2-4.8.1.dist-info/WHEEL
geoip2-4.8.1.dist-info/top_level.txt
geoip2-4.8.1.dist-info/RECORD
