Metadata-Version: 2.1
Name: geoip2
Version: 4.8.1
Summary: MaxMind GeoIP2 API
Author-email: Gregory Oschwald <goschwald@maxmind.com>
License: Apache License, Version 2.0
Project-URL: Homepage, https://www.maxmind.com/
Project-URL: Documentation, https://geoip2.readthedocs.org/
Project-URL: Source Code, https://github.com/maxmind/GeoIP2-python
Project-URL: Issue Tracker, https://github.com/maxmind/GeoIP2-python/issues
Classifier: Development Status :: 5 - Production/Stable
Classifier: Environment :: Web Environment
Classifier: Intended Audience :: Developers
Classifier: Intended Audience :: System Administrators
Classifier: License :: OSI Approved :: Apache Software License
Classifier: Programming Language :: Python
Classifier: Programming Language :: Python :: 3
Classifier: Programming Language :: Python :: 3.8
Classifier: Programming Language :: Python :: 3.9
Classifier: Programming Language :: Python :: 3.10
Classifier: Programming Language :: Python :: 3.11
Classifier: Programming Language :: Python :: 3.12
Classifier: Programming Language :: Python :: 3.13
Classifier: Topic :: Internet
Classifier: Topic :: Internet :: Proxy Servers
Requires-Python: >=3.8
License-File: LICENSE
Requires-Dist: aiohttp<4.0.0,>=3.6.2
Requires-Dist: maxminddb<3.0.0,>=2.5.1
Requires-Dist: requests<3.0.0,>=2.24.0
Provides-Extra: test
Requires-Dist: pytest-httpserver>=1.0.10; extra == "test"
